saturn_sync_protocol/__init__.py
saturn_sync_protocol/plugin/grpc_controller_pb2.py
saturn_sync_protocol/plugin/grpc_controller_pb2.pyi
saturn_sync_protocol/plugin/grpc_controller_pb2_grpc.py
saturn_sync_protocol/v1/__init__.py
saturn_sync_protocol/v1/saturnsync_pb2.py
saturn_sync_protocol/v1/saturnsync_pb2.pyi
saturn_sync_protocol/v1/saturnsync_pb2_grpc.py
saturn_sync_protocol-0.3.0.dist-info/METADATA
saturn_sync_protocol-0.3.0.dist-info/WHEEL
saturn_sync_protocol-0.3.0.dist-info/RECORD
